{
  "title": "Pola 3-S: Cara Efektif Memanfaatkan AI dalam Belajar dan Bekerja",
  "slug": "3s-memanfaatkan-ai",
  "image": "/images/b220a866-49f4-4dfb-9a39-25fe5cd9a7c5.jpg",
  "date": "2026-04-13",
  "author": "Raja Capybara",
  "tags": [
    "Teknologi",
    "AI",
    "Edukasi",
    "Pekerjaan"
  ],
  "excerpt": "Di era digital saat ini, Artificial Intelligence (AI) telah menjadi alat yang sangat membantu dalam berbagai aktivitas, baik dalam pembelajaran maupun pekerjaan. Namun, penggunaan AI yang tidak tepat dapat membuat seseorang hanya bergantung tanpa benar-benar memahami prosesnya. Oleh karena itu, diperlukan pendekatan yang terarah agar AI dapat dimanfaatkan secara optimal.",
  "body": "Di era digital saat ini, Artificial Intelligence (AI) telah menjadi alat yang sangat membantu dalam berbagai aktivitas, baik dalam pembelajaran maupun pekerjaan. Namun, penggunaan AI yang tidak tepat dapat membuat seseorang hanya bergantung tanpa benar-benar memahami prosesnya. Oleh karena itu, diperlukan pendekatan yang terarah agar AI dapat dimanfaatkan secara optimal.\n\nSalah satu pendekatan yang dapat digunakan adalah **Pola 3-S: Saring, Seleksi, Setel**. Pola ini membantu pengguna untuk tidak sekadar menerima hasil dari AI, tetapi juga mengolah dan menerapkannya secara bijak.\n\n---\n\n### 🔹 1. Saring (Input & Instruksi)\n\nTahap pertama adalah memberikan input yang jelas dan spesifik kepada AI. Pengguna perlu menyertakan konteks, tujuan, serta instruksi yang tepat agar AI dapat menghasilkan output yang relevan.\n\nPada tahap ini, AI berfungsi untuk menyaring informasi yang kompleks menjadi lebih sederhana dan terstruktur, sehingga lebih mudah dipahami.\n\n---\n\n### 🔹 2. Seleksi (Verifikasi & Filter)\n\nTahap kedua adalah melakukan seleksi terhadap hasil dari AI. Penting untuk diingat bahwa output AI tidak selalu sepenuhnya benar atau sesuai kebutuhan.\n\nOleh karena itu, pengguna perlu melakukan verifikasi, membandingkan dengan sumber lain, serta memilih informasi yang benar-benar relevan. Dengan cara ini, hasil yang digunakan menjadi lebih akurat dan tepat sasaran.\n\n---\n\n### 🔹 3. Setel (Penerapan)\n\nTahap terakhir adalah menerapkan hasil yang telah diseleksi ke dalam konteks nyata. Informasi yang telah dipahami kemudian diolah kembali dan digunakan dalam tugas, proyek, atau pekerjaan.\n\nDengan tahap ini, AI tidak hanya menjadi alat bantu, tetapi juga menjadi bagian dari proses berpikir dan pengambilan keputusan.\n\n---\n\n## 📚 Studi Kasus 1: Pembelajaran (Tugas Makalah)\n\nSeorang mahasiswa mendapatkan tugas untuk membuat makalah tentang keamanan aplikasi web.\n\n- **Saring:**  \nMahasiswa meminta AI untuk menjelaskan konsep dasar keamanan web beserta contoh kasus seperti SQL Injection dan XSS.\n- **Seleksi:**  \nHasil dari AI tidak langsung digunakan, tetapi dicek kembali, dipilih poin-poin penting, serta disesuaikan dengan referensi lain.\n- **Setel:**  \nMateri kemudian disusun ulang menjadi makalah dengan bahasa sendiri, ditambahkan pemahaman pribadi, serta disesuaikan dengan format yang diminta dosen.\n\n➡️ **Hasil:** Tugas dapat diselesaikan lebih cepat, sekaligus tetap memahami materi yang dipelajari.\n\n---\n\n## 💻 Studi Kasus 2: Pekerjaan (Pengembangan Fitur Login)\n\nSeorang developer ingin membuat fitur login pada aplikasi berbasis web.\n\n- **Saring:**  \nDeveloper meminta AI untuk membuat contoh implementasi login menggunakan React, Node.js, dan JWT.\n- **Seleksi:**  \nHasil dari AI diperiksa kembali, seperti memastikan penggunaan hashing password, validasi input, dan aspek keamanan lainnya.\n- **Setel:**  \nKode yang telah diseleksi kemudian diterapkan ke dalam project, disesuaikan dengan kebutuhan sistem dan struktur database yang digunakan.\n\n➡️ **Hasil:** Proses pengembangan menjadi lebih cepat, namun tetap sesuai dengan standar yang dibutuhkan.\n\n---\n\n## 🎯 Kesimpulan\n\nPola 3-S (Saring, Seleksi, Setel) merupakan pendekatan sederhana namun efektif dalam memanfaatkan AI. Dengan menerapkan ketiga tahap tersebut, pengguna dapat menjadikan AI sebagai alat bantu yang produktif, bukan sekadar sumber jawaban instan.\n\nPada akhirnya, AI bukan pengganti proses berpikir, melainkan alat untuk mempercepat dan memperkuat pemahaman. Kunci utamanya tetap pada bagaimana pengguna mampu menyaring, memilih, dan menerapkan informasi secara bijak."
}